mailrelay/__init__.py
mailrelay/admin.py
mailrelay/app_settings.py
mailrelay/apps.py
mailrelay/auth_hooks.py
mailrelay/managers.py
mailrelay/models.py
mailrelay/providers.py
mailrelay/tasks.py
mailrelay/urls.py
mailrelay/utils.py
mailrelay/views.py
mailrelay/core/__init__.py
mailrelay/core/xml_converter.py
mailrelay/migrations/0001_initial.py
mailrelay/migrations/0002_django4_update.py
mailrelay/migrations/0003_alter_discordcategory_options_and_more.py
mailrelay/migrations/__init__.py
mailrelay/static/mailrelay/mailrelay_logo.png
mailrelay/templates/admin/mailrelay/relayconfig/change_list.html
mailrelay/templates/mailrelay/base.html
mailrelay/templates/mailrelay/index.html
mailrelay/tests/__init__.py
mailrelay/tests/factories.py
mailrelay/tests/test_admin.py
mailrelay/tests/test_core_xml_converter.py
mailrelay/tests/test_integration.py
mailrelay/tests/test_models.py
mailrelay/tests/test_providers.py
mailrelay/tests/test_tasks.py
mailrelay/tests/test_utils.py
mailrelay/tests/test_views.py
aa_mailrelay-1.4.0.dist-info/LICENSE
aa_mailrelay-1.4.0.dist-info/WHEEL
aa_mailrelay-1.4.0.dist-info/METADATA
aa_mailrelay-1.4.0.dist-info/RECORD
