Metadata-Version: 2.1
Name: aa-mailrelay
Version: 1.4.0
Summary: An app for relaying Eve mails to Discord.
Author-email: Erik Kalkoken <kalkoken87@gmail.com>
Requires-Python: >=3.8
Classifier: Environment :: Web Environment
Classifier: Framework :: Django
Classifier: Framework :: Django :: 4.0
Classifier: Framework :: Django :: 4.2
Classifier: Intended Audience :: Developers
Classifier: License :: OSI Approved :: MIT License
Classifier: Operating System :: OS Independent
Classifier: Programming Language :: Python
Classifier: Programming Language :: Python :: 3.8
Classifier: Programming Language :: Python :: 3.9
Classifier: Programming Language :: Python :: 3.10
Classifier: Programming Language :: Python :: 3.11
Classifier: Topic :: Internet :: WWW/HTTP
Classifier: Topic :: Internet :: WWW/HTTP :: Dynamic Content
Requires-Dist: aa-memberaudit>=3.7.0
Requires-Dist: allianceauth-app-utils>=1.19
Requires-Dist: allianceauth>=3
Requires-Dist: discordproxy>=1.3.2
Requires-Dist: django-eveuniverse>=1
Project-URL: Homepage, https://gitlab.com/ErikKalkoken/aa-mailrelay
